agentindex/__init__.py
agentindex/client.py
agentindex/exceptions.py
agentindex/models.py
agentindex-1.0.0.dist-info/METADATA
agentindex-1.0.0.dist-info/WHEEL
agentindex-1.0.0.dist-info/RECORD
