Metadata-Version: 2.4
Name: agentindex
Version: 1.0.0
Summary: Official Python SDK for Agent Index - The discovery layer for x402 AI agents
Project-URL: Homepage, https://theagentindex.app
Project-URL: Documentation, https://theagentindex.app/docs
Project-URL: Repository, https://github.com/402-agent/agentindex-python
Project-URL: Issues, https://github.com/402-agent/agentindex-python/issues
Author-email: 402 Agent Inc <hello@theagentindex.app>
License-Expression: MIT
Keywords: agent-discovery,agent-index,ai-agents,base,coinbase,langchain,x402
Classifier: Development Status :: 4 - Beta
Classifier: Intended Audience :: Developers
Classifier: License :: OSI Approved :: MIT License
Classifier: Programming Language :: Python :: 3
Classifier: Programming Language :: Python :: 3.9
Classifier: Programming Language :: Python :: 3.10
Classifier: Programming Language :: Python :: 3.11
Classifier: Programming Language :: Python :: 3.12
Classifier: Topic :: Internet :: WWW/HTTP
Classifier: Topic :: Software Development :: Libraries :: Python Modules
Requires-Python: >=3.9
Requires-Dist: httpx>=0.25.0
Requires-Dist: pydantic>=2.0.0
Provides-Extra: dev
Requires-Dist: pytest; extra == 'dev'
Requires-Dist: pytest-asyncio; extra == 'dev'
Requires-Dist: ruff; extra == 'dev'
Provides-Extra: langchain
Requires-Dist: langchain>=0.1.0; extra == 'langchain'
